mkdocs_ivory/404.html
mkdocs_ivory/__init__.py
mkdocs_ivory/base.html
mkdocs_ivory/breadcrumbs.html
mkdocs_ivory/footer.html
mkdocs_ivory/main.html
mkdocs_ivory/mkdocs_theme.yml
mkdocs_ivory/nav.html
mkdocs_ivory/repo.html
mkdocs_ivory/search.html
mkdocs_ivory/searchbox.html
mkdocs_ivory/toc.html
mkdocs_ivory/css/theme.css
mkdocs_ivory/img/favicon.ico
mkdocs_ivory/js/theme.js
mkdocs_ivory-0.4.6.dist-info/LICENSE
mkdocs_ivory-0.4.6.dist-info/METADATA
mkdocs_ivory-0.4.6.dist-info/WHEEL
mkdocs_ivory-0.4.6.dist-info/entry_points.txt
mkdocs_ivory-0.4.6.dist-info/top_level.txt
mkdocs_ivory-0.4.6.dist-info/RECORD
