Metadata-Version: 2.1
Name: mkdocs-ivory
Version: 0.4.6
Summary: Ivory theme for MkDocs
Home-page: https://github.com/daizutabi/mkdocs-ivory
Author: daizutabi
Author-email: daizutabi@gmail.com
License: MIT
Platform: UNKNOWN
